[
    {
        "_ansible_ignore_errors": null, 
        "_ansible_item_result": true, 
        "_ansible_no_log": false, 
        "_ansible_parsed": true, 
        "changed": false, 
        "cmd": [
            "diff", 
            "/etc/ansible/playbooks/master/mas/mmail.conf", 
            "/etc/ansible/playbooks/uk3/mas/mas4/mmail.conf"
        ], 
        "delta": "0:00:00.002267", 
        "end": "2018-10-08 02:21:30.045647", 
        "failed": false, 
        "failed_when_result": false, 
        "invocation": {
            "module_args": {
                "_raw_params": "diff /etc/ansible/playbooks/master/mas/mmail.conf /etc/ansible/playbooks/uk3/mas/mas4/mmail.conf", 
                "_uses_shell": false, 
                "chdir": "/etc/ansible/playbooks/", 
                "creates": null, 
                "executable": null, 
                "removes": null, 
                "stdin": null, 
                "warn": true
            }
        }, 
        "item": "mas4", 
        "rc": 0, 
        "start": "2018-10-08 02:21:30.043380", 
        "stderr": "", 
        "stderr_lines": [], 
        "stdout": "", 
        "stdout_lines": []
    }, 
    {
        "_ansible_ignore_errors": null, 
        "_ansible_item_result": true, 
        "_ansible_no_log": false, 
        "_ansible_parsed": true, 
        "changed": false, 
        "cmd": [
            "diff", 
            "/etc/ansible/playbooks/master/mas/mmail.conf", 
            "/etc/ansible/playbooks/uk3/mas/mas3/mmail.conf"
        ], 
        "delta": "0:00:00.018849", 
        "end": "2018-10-08 02:21:30.287006", 
        "failed": false, 
        "failed_when_result": false, 
        "invocation": {
            "module_args": {
                "_raw_params": "diff /etc/ansible/playbooks/master/mas/mmail.conf /etc/ansible/playbooks/uk3/mas/mas3/mmail.conf", 
                "_uses_shell": false, 
                "chdir": "/etc/ansible/playbooks/", 
                "creates": null, 
                "executable": null, 
                "removes": null, 
                "stdin": null, 
                "warn": true
            }
        }, 
        "item": "mas3", 
        "rc": 0, 
        "start": "2018-10-08 02:21:30.268157", 
        "stderr": "", 
        "stderr_lines": [], 
        "stdout": "", 
        "stdout_lines": []
    }, 
    {
        "_ansible_ignore_errors": null, 
        "_ansible_item_result": true, 
        "_ansible_no_log": false, 
        "_ansible_parsed": true, 
        "changed": false, 
        "cmd": [
            "diff", 
            "/etc/ansible/playbooks/master/mas/mmail.conf", 
            "/etc/ansible/playbooks/uk3/mas/mas2/mmail.conf"
        ], 
        "delta": "0:00:00.001915", 
        "end": "2018-10-08 02:21:30.528496", 
        "failed": false, 
        "failed_when_result": false, 
        "invocation": {
            "module_args": {
                "_raw_params": "diff /etc/ansible/playbooks/master/mas/mmail.conf /etc/ansible/playbooks/uk3/mas/mas2/mmail.conf", 
                "_uses_shell": false, 
                "chdir": "/etc/ansible/playbooks/", 
                "creates": null, 
                "executable": null, 
                "removes": null, 
                "stdin": null, 
                "warn": true
            }
        }, 
        "item": "mas2", 
        "rc": 0, 
        "start": "2018-10-08 02:21:30.526581", 
        "stderr": "", 
        "stderr_lines": [], 
        "stdout": "", 
        "stdout_lines": []
    }, 
    {
        "_ansible_ignore_errors": null, 
        "_ansible_item_result": true, 
        "_ansible_no_log": false, 
        "_ansible_parsed": true, 
        "changed": false, 
        "cmd": [
            "diff", 
            "/etc/ansible/playbooks/master/mas/mmail.conf", 
            "/etc/ansible/playbooks/uk3/mas/mas1/mmail.conf"
        ], 
        "delta": "0:00:00.001499", 
        "end": "2018-10-08 02:21:30.754118", 
        "failed": false, 
        "failed_when_result": false, 
        "invocation": {
            "module_args": {
                "_raw_params": "diff /etc/ansible/playbooks/master/mas/mmail.conf /etc/ansible/playbooks/uk3/mas/mas1/mmail.conf", 
                "_uses_shell": false, 
                "chdir": "/etc/ansible/playbooks/", 
                "creates": null, 
                "executable": null, 
                "removes": null, 
                "stdin": null, 
                "warn": true
            }
        }, 
        "item": "mas1", 
        "rc": 0, 
        "start": "2018-10-08 02:21:30.752619", 
        "stderr": "", 
        "stderr_lines": [], 
        "stdout": "", 
        "stdout_lines": []
    }
]